terminalbot/__init__.py
terminalbot/bot.py
terminalbot/cli.py
terminalbot/terminalbot_cookies.json
terminalbot-2.0.0.dist-info/LICENSE
terminalbot-2.0.0.dist-info/METADATA
terminalbot-2.0.0.dist-info/WHEEL
terminalbot-2.0.0.dist-info/entry_points.txt
terminalbot-2.0.0.dist-info/top_level.txt
terminalbot-2.0.0.dist-info/RECORD
