Metadata-Version: 2.1
Name: terminalbot
Version: 2.0.0
Summary: A package to interact with a Telegram group by sending and receiving messages
Home-page: https://mrfidal.in/cyber-security/terminalbot
Author: Fidal
Author-email: mrfidal@proton.me
Keywords: telegram bot messaging automation
Classifier: Programming Language :: Python :: 3
Classifier: License :: OSI Approved :: MIT License
Classifier: Operating System :: OS Independent
Requires-Python: >=3.6
License-File: LICENSE
Requires-Dist: requests
